neutronclient/__init__.py
neutronclient/_i18n.py
neutronclient/client.py
neutronclient/version.py
neutronclient/common/__init__.py
neutronclient/common/clientmanager.py
neutronclient/common/constants.py
neutronclient/common/exceptions.py
neutronclient/common/extension.py
neutronclient/common/serializer.py
neutronclient/common/utils.py
neutronclient/common/validators.py
neutronclient/neutron/__init__.py
neutronclient/neutron/client.py
neutronclient/neutron/v2_0/__init__.py
neutronclient/neutron/v2_0/address_scope.py
neutronclient/neutron/v2_0/agent.py
neutronclient/neutron/v2_0/agentscheduler.py
neutronclient/neutron/v2_0/auto_allocated_topology.py
neutronclient/neutron/v2_0/availability_zone.py
neutronclient/neutron/v2_0/dns.py
neutronclient/neutron/v2_0/extension.py
neutronclient/neutron/v2_0/floatingip.py
neutronclient/neutron/v2_0/metering.py
neutronclient/neutron/v2_0/network.py
neutronclient/neutron/v2_0/network_ip_availability.py
neutronclient/neutron/v2_0/port.py
neutronclient/neutron/v2_0/purge.py
neutronclient/neutron/v2_0/quota.py
neutronclient/neutron/v2_0/rbac.py
neutronclient/neutron/v2_0/router.py
neutronclient/neutron/v2_0/securitygroup.py
neutronclient/neutron/v2_0/servicetype.py
neutronclient/neutron/v2_0/subnet.py
neutronclient/neutron/v2_0/subnetpool.py
neutronclient/neutron/v2_0/tag.py
neutronclient/neutron/v2_0/bgp/__init__.py
neutronclient/neutron/v2_0/bgp/dragentscheduler.py
neutronclient/neutron/v2_0/bgp/peer.py
neutronclient/neutron/v2_0/bgp/speaker.py
neutronclient/neutron/v2_0/contrib/__init__.py
neutronclient/neutron/v2_0/contrib/_fox_sockets.py
neutronclient/neutron/v2_0/flavor/__init__.py
neutronclient/neutron/v2_0/flavor/flavor.py
neutronclient/neutron/v2_0/flavor/flavor_profile.py
neutronclient/neutron/v2_0/fw/__init__.py
neutronclient/neutron/v2_0/fw/firewall.py
neutronclient/neutron/v2_0/fw/firewallpolicy.py
neutronclient/neutron/v2_0/fw/firewallrule.py
neutronclient/neutron/v2_0/lb/__init__.py
python_neutronclient-11.7.0.dist-info/licenses/AUTHORS
python_neutronclient-11.7.0.dist-info/licenses/LICENSE
python_neutronclient-11.7.0.dist-info/METADATA
python_neutronclient-11.7.0.dist-info/WHEEL
python_neutronclient-11.7.0.dist-info/entry_points.txt
python_neutronclient-11.7.0.dist-info/pbr.json
python_neutronclient-11.7.0.dist-info/top_level.txt
python_neutronclient-11.7.0.dist-info/RECORD
