Metadata-Version: 2.4
Name: python-neutronclient
Version: 11.7.0
Summary: CLI and Client Library for OpenStack Networking
Home-page: https://docs.openstack.org/python-neutronclient/latest/
Author: OpenStack Networking Project
Author-email: openstack-discuss@lists.openstack.org
Classifier: Environment :: OpenStack
Classifier: Intended Audience :: Developers
Classifier: Intended Audience :: Information Technology
Classifier: Intended Audience :: System Administrators
Classifier: License :: OSI Approved :: Apache Software License
Classifier: Operating System :: POSIX :: Linux
Classifier: Programming Language :: Python
Classifier: Programming Language :: Python :: Implementation :: CPython
Classifier: Programming Language :: Python :: 3 :: Only
Classifier: Programming Language :: Python :: 3
Classifier: Programming Language :: Python :: 3.9
Classifier: Programming Language :: Python :: 3.10
Classifier: Programming Language :: Python :: 3.11
Classifier: Programming Language :: Python :: 3.12
Requires-Python: >=3.9
License-File: LICENSE
License-File: AUTHORS
Requires-Dist: pbr!=2.1.0,>=2.0.0
Requires-Dist: cliff>=3.4.0
Requires-Dist: debtcollector>=1.2.0
Requires-Dist: netaddr>=0.7.18
Requires-Dist: openstacksdk>=1.5.0
Requires-Dist: osc-lib>=1.12.0
Requires-Dist: oslo.i18n>=3.15.3
Requires-Dist: oslo.log>=3.36.0
Requires-Dist: oslo.serialization!=2.19.1,>=2.18.0
Requires-Dist: oslo.utils>=3.33.0
Requires-Dist: keystoneauth1>=3.8.0
Requires-Dist: python-keystoneclient>=3.8.0
Requires-Dist: requests>=2.14.2
Dynamic: author
Dynamic: author-email
Dynamic: classifier
Dynamic: description
Dynamic: home-page
Dynamic: license-file
Dynamic: requires-dist
Dynamic: requires-python
Dynamic: summary
